springgen/__init__.py
springgen/spring_helper.py
springgen/spring_templates.py
springgen/springgen.py
springgen/utils.py
springgen/templates/java/_imports.java.j2
springgen/templates/java/controller.java.j2
springgen/templates/java/entity.java.j2
springgen/templates/java/repository.java.j2
springgen/templates/java/service.java.j2
springgen/templates/java/service_impl.java.j2
springgen-1.0.2.dist-info/METADATA
springgen-1.0.2.dist-info/WHEEL
springgen-1.0.2.dist-info/entry_points.txt
springgen-1.0.2.dist-info/top_level.txt
springgen-1.0.2.dist-info/RECORD
