Metadata-Version: 2.4
Name: springgen
Version: 1.0.2
Summary: Interactive Spring Boot CRUD CLI
Home-page: https://github.com/Ajoy-1704001/springgen
Author: Ajoy Deb Nath
License: MIT
Classifier: Programming Language :: Python :: 3
Classifier: Operating System :: OS Independent
Classifier: Intended Audience :: Developers
Classifier: License :: OSI Approved :: MIT License
Requires-Python: >=3.8
Requires-Dist: pyfiglet
Requires-Dist: termcolor
Requires-Dist: jinja2
Requires-Dist: pyyaml
Dynamic: author
Dynamic: classifier
Dynamic: description
Dynamic: description-content-type
Dynamic: home-page
Dynamic: license
Dynamic: requires-dist
Dynamic: requires-python
Dynamic: summary
